aanalyticssegg/__init__.py
aanalyticssegg/__version__.py
aanalyticssegg/actCreateSeg.py
aanalyticssegg/actGetSeg.py
aanalyticssegg/actLibrarySeg.py
aanalyticssegg/actUpdateSeg.py
aanalyticssegg-0.0.1.dist-info/METADATA
aanalyticssegg-0.0.1.dist-info/WHEEL
aanalyticssegg-0.0.1.dist-info/top_level.txt
aanalyticssegg-0.0.1.dist-info/RECORD
