Metadata-Version: 2.1
Name: aanalyticssegg
Version: 0.0.1
Summary: automation tool to crud segments
Home-page: https://github.com/SunkyeongLee/aanalyticssegg
Author: Sunkyeong Lee
Author-email: sunkyeong.lee@concentrix.com
License: UNKNOWN
Platform: UNKNOWN
Classifier: Programming Language :: Python :: 3
Classifier: License :: OSI Approved :: MIT License
Classifier: Operating System :: OS Independent
Requires-Python: >=3.6
